LICENSE
MANIFEST.in
README.md
pyproject.toml
setup.py
src/kepderiv/__init__.py
src/kepderiv/libkeplerian.c
src/kepderiv/libkeplerian.h
src/kepderiv/pywrapkeplerian.c
src/kepderiv.egg-info/PKG-INFO
src/kepderiv.egg-info/SOURCES.txt
src/kepderiv.egg-info/dependency_links.txt
src/kepderiv.egg-info/requires.txt
src/kepderiv.egg-info/top_level.txt
tests/test_kepderiv.py