Metadata-Version: 2.4
Name: kepderiv
Version: 1.0.9
Summary: Keplerian modeling and derivatives for radial velocities and astrometry analyses.
Author-email: Jean-Baptiste Delisle <jean-baptiste.delisle@unige.ch>
Project-URL: Homepage, https://gitlab.unige.ch/delisle/kepderiv
Project-URL: Issues, https://gitlab.unige.ch/delisle/kepderiv/-/issues
Classifier: Programming Language :: Python :: 3
Classifier: License :: OSI Approved :: European Union Public Licence 1.2 (EUPL 1.2)
Classifier: Operating System :: OS Independent
Requires-Python: >=3.9
License-File: LICENSE
Requires-Dist: numpy>=1.19
Dynamic: license-file
